sawtooth_processor_test/__init__.py
sawtooth_processor_test/message_factory.py
sawtooth_processor_test/message_types.py
sawtooth_processor_test/mock_validator.py
sawtooth_processor_test/transaction_processor_test_case.py
sawtooth_sdk/__init__.py
sawtooth_sdk/consensus/__init__.py
sawtooth_sdk/consensus/driver.py
sawtooth_sdk/consensus/engine.py
sawtooth_sdk/consensus/exceptions.py
sawtooth_sdk/consensus/service.py
sawtooth_sdk/consensus/zmq_driver.py
sawtooth_sdk/consensus/zmq_service.py
sawtooth_sdk/messaging/__init__.py
sawtooth_sdk/messaging/exceptions.py
sawtooth_sdk/messaging/future.py
sawtooth_sdk/messaging/stream.py
sawtooth_sdk/processor/__init__.py
sawtooth_sdk/processor/config.py
sawtooth_sdk/processor/context.py
sawtooth_sdk/processor/core.py
sawtooth_sdk/processor/exceptions.py
sawtooth_sdk/processor/handler.py
sawtooth_sdk/processor/log.py
sawtooth_sdk/protobuf/__init__.py
sawtooth_sdk/protobuf/authorization_pb2.py
sawtooth_sdk/protobuf/batch_pb2.py
sawtooth_sdk/protobuf/block_info_pb2.py
sawtooth_sdk/protobuf/block_pb2.py
sawtooth_sdk/protobuf/client_batch_pb2.py
sawtooth_sdk/protobuf/client_batch_submit_pb2.py
sawtooth_sdk/protobuf/client_block_pb2.py
sawtooth_sdk/protobuf/client_event_pb2.py
sawtooth_sdk/protobuf/client_list_control_pb2.py
sawtooth_sdk/protobuf/client_peers_pb2.py
sawtooth_sdk/protobuf/client_receipt_pb2.py
sawtooth_sdk/protobuf/client_state_pb2.py
sawtooth_sdk/protobuf/client_status_pb2.py
sawtooth_sdk/protobuf/client_transaction_pb2.py
sawtooth_sdk/protobuf/consensus_pb2.py
sawtooth_sdk/protobuf/events_pb2.py
sawtooth_sdk/protobuf/genesis_pb2.py
sawtooth_sdk/protobuf/identity_pb2.py
sawtooth_sdk/protobuf/merkle_pb2.py
sawtooth_sdk/protobuf/network_pb2.py
sawtooth_sdk/protobuf/processor_pb2.py
sawtooth_sdk/protobuf/setting_pb2.py
sawtooth_sdk/protobuf/state_context_pb2.py
sawtooth_sdk/protobuf/transaction_pb2.py
sawtooth_sdk/protobuf/transaction_receipt_pb2.py
sawtooth_sdk-1.2.5.dist-info/DESCRIPTION.rst
sawtooth_sdk-1.2.5.dist-info/METADATA
sawtooth_sdk-1.2.5.dist-info/RECORD
sawtooth_sdk-1.2.5.dist-info/WHEEL
sawtooth_sdk-1.2.5.dist-info/metadata.json
sawtooth_sdk-1.2.5.dist-info/top_level.txt
