Metadata-Version: 2.1
Name: sawtooth-sdk
Version: 1.2.5
Summary: Sawtooth Python SDK
Home-page: https://github.com/hyperledger/sawtooth-sdk-python
Author: Hyperledger Sawtooth
License: UNKNOWN
Platform: UNKNOWN
License-File: LICENSE
License-File: NOTICES
